{
  "season": 29,
  "season_name": "Survivor: San Juan del Sur",
  "challenges": [
    {
      "challenge_id": 1,
      "episode": 1,
      "day": null,
      "challenge_type": "Reward",
      "outcome_type": "Tribal",
      "winners": [
        "Drew",
        "Kelley",
        "Julie",
        "Jeremy",
        "Reed",
        "Jon",
        "Keith",
        "Missy",
        "Natalie"
      ]
    },
    {
      "challenge_id": 2,
      "episode": 1,
      "day": null,
      "challenge_type": "Immunity",
      "outcome_type": "Tribal",
      "winners": [
        "Drew",
        "Kelley",
        "Julie",
        "Jeremy",
        "Reed",
        "Jon",
        "Keith",
        "Missy",
        "Natalie"
      ]
    },
    {
      "challenge_id": 3,
      "episode": 2,
      "day": null,
      "challenge_type": "Reward",
      "outcome_type": "Tribal",
      "winners": [
        "Drew",
        "Kelley",
        "Julie",
        "Jeremy",
        "Reed",
        "Jon",
        "Keith",
        "Missy",
        "Natalie"
      ]
    },
    {
      "challenge_id": 4,
      "episode": 2,
      "day": null,
      "challenge_type": "Immunity",
      "outcome_type": "Tribal",
      "winners": [
        "Drew",
        "Kelley",
        "Julie",
        "Jeremy",
        "Reed",
        "Jon",
        "Keith",
        "Missy",
        "Natalie"
      ]
    },
    {
      "challenge_id": 5,
      "episode": 3,
      "day": null,
      "challenge_type": "Reward",
      "outcome_type": "Tribal",
      "winners": [
        "Dale",
        "Josh",
        "Wes",
        "Alec",
        "Baylor",
        "Jaclyn"
      ]
    },
    {
      "challenge_id": 6,
      "episode": 3,
      "day": null,
      "challenge_type": "Immunity",
      "outcome_type": "Tribal",
      "winners": [
        "Drew",
        "Kelley",
        "Julie",
        "Jeremy",
        "Reed",
        "Jon",
        "Keith",
        "Missy",
        "Natalie"
      ]
    },
    {
      "challenge_id": 7,
      "episode": 4,
      "day": null,
      "challenge_type": "Reward",
      "outcome_type": "Tribal",
      "winners": [
        "Drew",
        "Kelley",
        "Julie",
        "Jeremy",
        "Reed",
        "Jon",
        "Keith",
        "Missy",
        "Natalie"
      ]
    },
    {
      "challenge_id": 8,
      "episode": 4,
      "day": null,
      "challenge_type": "Immunity",
      "outcome_type": "Tribal",
      "winners": [
        "Dale",
        "Josh",
        "Wes",
        "Alec",
        "Baylor",
        "Jaclyn"
      ]
    },
    {
      "challenge_id": 9,
      "episode": 5,
      "day": null,
      "challenge_type": "Immunity",
      "outcome_type": "Tribal",
      "winners": [
        "Julie",
        "Josh",
        "Jeremy",
        "Wes",
        "Reed",
        "Alec",
        "Natalie"
      ]
    },
    {
      "challenge_id": 10,
      "episode": 6,
      "day": null,
      "challenge_type": "Reward",
      "outcome_type": "Tribal",
      "winners": [
        "Julie",
        "Josh",
        "Jeremy",
        "Wes",
        "Reed",
        "Alec",
        "Natalie"
      ]
    },
    {
      "challenge_id": 11,
      "episode": 6,
      "day": null,
      "challenge_type": "Immunity",
      "outcome_type": "Tribal",
      "winners": [
        "Julie",
        "Josh",
        "Jeremy",
        "Wes",
        "Reed",
        "Alec",
        "Natalie"
      ]
    },
    {
      "challenge_id": 12,
      "episode": 7,
      "day": null,
      "challenge_type": "Immunity",
      "outcome_type": "Individual",
      "winners": [
        "Keith"
      ]
    },
    {
      "challenge_id": 13,
      "episode": 8,
      "day": null,
      "challenge_type": "Reward",
      "outcome_type": "Team",
      "winners": [
        "Jeremy",
        "Wes",
        "Reed",
        "Keith",
        "Natalie"
      ]
    },
    {
      "challenge_id": 14,
      "episode": 8,
      "day": null,
      "challenge_type": "Immunity",
      "outcome_type": "Individual",
      "winners": [
        "Jeremy"
      ]
    },
    {
      "challenge_id": 15,
      "episode": 9,
      "day": null,
      "challenge_type": "Reward",
      "outcome_type": "Team",
      "winners": [
        "Jeremy",
        "Reed",
        "Alec",
        "Baylor",
        "Natalie"
      ]
    },
    {
      "challenge_id": 16,
      "episode": 9,
      "day": null,
      "challenge_type": "Immunity",
      "outcome_type": "Individual",
      "winners": [
        "Baylor"
      ]
    },
    {
      "challenge_id": 17,
      "episode": 10,
      "day": null,
      "challenge_type": "Reward",
      "outcome_type": "Team",
      "winners": [
        "Reed",
        "Alec",
        "Jon",
        "Jaclyn"
      ]
    },
    {
      "challenge_id": 18,
      "episode": 10,
      "day": null,
      "challenge_type": "Immunity",
      "outcome_type": "Individual",
      "winners": [
        "Reed"
      ]
    },
    {
      "challenge_id": 19,
      "episode": 11,
      "day": null,
      "challenge_type": "Reward",
      "outcome_type": "Individual",
      "winners": [
        "Missy"
      ]
    },
    {
      "challenge_id": 20,
      "episode": 11,
      "day": null,
      "challenge_type": "Immunity",
      "outcome_type": "Individual",
      "winners": [
        "Keith"
      ]
    },
    {
      "challenge_id": 21,
      "episode": 12,
      "day": null,
      "challenge_type": "Reward",
      "outcome_type": "Individual",
      "winners": [
        "Natalie"
      ]
    },
    {
      "challenge_id": 22,
      "episode": 12,
      "day": null,
      "challenge_type": "Immunity",
      "outcome_type": "Individual",
      "winners": [
        "Jon"
      ]
    },
    {
      "challenge_id": 23,
      "episode": 13,
      "day": null,
      "challenge_type": "Reward",
      "outcome_type": "Team",
      "winners": [
        "Jon",
        "Keith",
        "Missy"
      ]
    },
    {
      "challenge_id": 24,
      "episode": 13,
      "day": null,
      "challenge_type": "Immunity",
      "outcome_type": "Individual",
      "winners": [
        "Natalie"
      ]
    },
    {
      "challenge_id": 25,
      "episode": 14,
      "day": null,
      "challenge_type": "Reward",
      "outcome_type": "Individual",
      "winners": [
        "Keith"
      ]
    },
    {
      "challenge_id": 26,
      "episode": 14,
      "day": null,
      "challenge_type": "Immunity",
      "outcome_type": "Individual",
      "winners": [
        "Keith"
      ]
    },
    {
      "challenge_id": 27,
      "episode": 14,
      "day": null,
      "challenge_type": "Immunity",
      "outcome_type": "Individual",
      "winners": [
        "Jaclyn"
      ]
    }
  ]
}