{
  "season": 34,
  "season_name": "Survivor: Game Changers",
  "challenges": [
    {
      "challenge_id": 1,
      "episode": 1,
      "day": null,
      "challenge_type": "Reward",
      "outcome_type": "Tribal",
      "winners": [
        "Cirie",
        "Ozzy",
        "J.T.",
        "Andrea",
        "Brad",
        "Sarah",
        "Sierra",
        "Debbie",
        "Tai",
        "Zeke"
      ]
    },
    {
      "challenge_id": 2,
      "episode": 1,
      "day": null,
      "challenge_type": "Immunity and Reward",
      "outcome_type": "Tribal",
      "winners": [
        "Cirie",
        "Ozzy",
        "J.T.",
        "Andrea",
        "Brad",
        "Sarah",
        "Sierra",
        "Debbie",
        "Tai",
        "Zeke"
      ]
    },
    {
      "challenge_id": 3,
      "episode": 1,
      "day": null,
      "challenge_type": "Immunity and Reward",
      "outcome_type": "Tribal",
      "winners": [
        "Cirie",
        "Ozzy",
        "J.T.",
        "Andrea",
        "Brad",
        "Sarah",
        "Sierra",
        "Debbie",
        "Tai",
        "Zeke"
      ]
    },
    {
      "challenge_id": 4,
      "episode": 2,
      "day": null,
      "challenge_type": "Immunity and Reward",
      "outcome_type": "Tribal",
      "winners": [
        "Jeff",
        "Sandra",
        "J.T.",
        "Malcolm",
        "Aubry",
        "Michaela",
        "Cirie",
        "Ozzy",
        "Andrea",
        "Troyzan",
        "Sarah",
        "Zeke"
      ]
    },
    {
      "challenge_id": 5,
      "episode": 3,
      "day": null,
      "challenge_type": "Reward",
      "outcome_type": "Tribal",
      "winners": [
        "Brad",
        "Hali",
        "Sierra",
        "Debbie",
        "Tai",
        "Jeff",
        "Sandra",
        "J.T.",
        "Malcolm",
        "Aubry",
        "Michaela"
      ]
    },
    {
      "challenge_id": 6,
      "episode": 3,
      "day": null,
      "challenge_type": "Immunity",
      "outcome_type": "Tribal",
      "winners": [
        "Cirie",
        "Ozzy",
        "Andrea",
        "Troyzan",
        "Sarah",
        "Zeke"
      ]
    },
    {
      "challenge_id": 7,
      "episode": 4,
      "day": null,
      "challenge_type": "Reward",
      "outcome_type": "Tribal",
      "winners": [
        "Jeff",
        "Sandra",
        "J.T.",
        "Aubry",
        "Michaela",
        "Cirie",
        "Ozzy",
        "Andrea",
        "Troyzan",
        "Sarah"
      ]
    },
    {
      "challenge_id": 8,
      "episode": 4,
      "day": null,
      "challenge_type": "Immunity",
      "outcome_type": "Tribal",
      "winners": [
        "Brad",
        "Hali",
        "Sierra",
        "Debbie",
        "Tai",
        "Cirie",
        "Ozzy",
        "Andrea",
        "Troyzan",
        "Sarah",
        "Zeke"
      ]
    },
    {
      "challenge_id": 9,
      "episode": 5,
      "day": null,
      "challenge_type": "Immunity",
      "outcome_type": "Tribal",
      "winners": [
        "Brad",
        "Hali",
        "Sierra",
        "Debbie",
        "Tai"
      ]
    },
    {
      "challenge_id": 10,
      "episode": 6,
      "day": null,
      "challenge_type": "Reward",
      "outcome_type": "Tribal",
      "winners": [
        "Debbie",
        "Tai",
        "Jeff",
        "Ozzy",
        "Andrea",
        "Sarah",
        "Zeke"
      ]
    },
    {
      "challenge_id": 11,
      "episode": 6,
      "day": null,
      "challenge_type": "Immunity",
      "outcome_type": "Tribal",
      "winners": [
        "Brad",
        "Hali",
        "Sierra",
        "Debbie",
        "Tai"
      ]
    },
    {
      "challenge_id": 12,
      "episode": 7,
      "day": null,
      "challenge_type": "Immunity",
      "outcome_type": "Individual",
      "winners": [
        "Andrea"
      ]
    },
    {
      "challenge_id": 13,
      "episode": 7,
      "day": null,
      "challenge_type": "Reward",
      "outcome_type": "Team",
      "winners": [
        "Ozzy",
        "Andrea",
        "Troyzan",
        "Debbie",
        "Tai",
        "Zeke"
      ]
    },
    {
      "challenge_id": 14,
      "episode": 7,
      "day": null,
      "challenge_type": "Immunity",
      "outcome_type": "Individual",
      "winners": [
        "Tai"
      ]
    },
    {
      "challenge_id": 15,
      "episode": 8,
      "day": null,
      "challenge_type": "Reward",
      "outcome_type": "Team",
      "winners": [
        "Andrea",
        "Brad",
        "Sierra",
        "Debbie",
        "Aubry"
      ]
    },
    {
      "challenge_id": 16,
      "episode": 8,
      "day": null,
      "challenge_type": "Immunity",
      "outcome_type": "Individual",
      "winners": [
        "Troyzan"
      ]
    },
    {
      "challenge_id": 17,
      "episode": 9,
      "day": null,
      "challenge_type": "Reward",
      "outcome_type": "Team",
      "winners": [
        "Andrea",
        "Brad",
        "Sarah",
        "Aubry",
        "Zeke"
      ]
    },
    {
      "challenge_id": 18,
      "episode": 9,
      "day": null,
      "challenge_type": "Immunity",
      "outcome_type": "Individual",
      "winners": [
        "Andrea"
      ]
    },
    {
      "challenge_id": 19,
      "episode": 10,
      "day": null,
      "challenge_type": "Reward",
      "outcome_type": "Team",
      "winners": [
        "Andrea",
        "Brad",
        "Aubry"
      ]
    },
    {
      "challenge_id": 20,
      "episode": 10,
      "day": null,
      "challenge_type": "Immunity",
      "outcome_type": "Individual",
      "winners": [
        "Brad"
      ]
    },
    {
      "challenge_id": 21,
      "episode": 11,
      "day": null,
      "challenge_type": "Immunity",
      "outcome_type": "Individual",
      "winners": [
        "Aubry"
      ]
    },
    {
      "challenge_id": 22,
      "episode": 11,
      "day": null,
      "challenge_type": "Immunity",
      "outcome_type": "Individual",
      "winners": [
        "Brad"
      ]
    },
    {
      "challenge_id": 23,
      "episode": 12,
      "day": null,
      "challenge_type": "Immunity and Reward",
      "outcome_type": "Individual",
      "winners": [
        "Brad"
      ]
    },
    {
      "challenge_id": 24,
      "episode": 12,
      "day": null,
      "challenge_type": "Immunity",
      "outcome_type": "Individual",
      "winners": [
        "Brad"
      ]
    },
    {
      "challenge_id": 25,
      "episode": 12,
      "day": null,
      "challenge_type": "Immunity",
      "outcome_type": "Individual",
      "winners": [
        "Brad"
      ]
    }
  ]
}